sabyvok
