Metadata-Version: 2.1
Name: sabyvok
Version: 1.0.1
Summary: Saby Vok API client
Home-page: https://github.com/saby/vok/tree/main/client-py
Author: Igor Veselov
Author-email: mail@veseloff.net
License: UNKNOWN
Platform: UNKNOWN
